{
	"name": "Урок 19",
	"kanji": [
		{
			"s": "辞",
			"on": [],
			"kun": [],
			"t": [
				"resign"
			]
		},
		{
			"s": "辺",
			"on": [
				"ヘン"
			],
			"kun": [
				"あたり",
				"べ"
			],
			"t": [
				"окрестности",
				"берег",
				"граница"
			]
		},
		{
			"s": "連",
			"on": [
				"レン"
			],
			"kun": [
				"つれる",
				"つらなる"
			],
			"t": [
				"брать с собой",
				"соединение",
				"группа",
				"компания"
			]
		},
		{
			"s": "達",
			"on": [
				"タツ",
				"タチ"
			],
			"kun": [],
			"t": [
				"достигать",
				"доставлять",
				"суффикс множественного числа"
			]
		},
		{
			"s": "選",
			"on": [
				"セン"
			],
			"kun": [
				"えらぶ"
			],
			"t": [
				"выбирать"
			]
		},
		{
			"s": "郡",
			"on": [],
			"kun": [],
			"t": [
				"округ"
			]
		},
		{
			"s": "量",
			"on": [
				"リョー"
			],
			"kun": [
				"はかる"
			],
			"t": [
				"количество",
				"вес",
				"объём",
				"измерять"
			]
		},
		{
			"s": "録",
			"on": [],
			"kun": [],
			"t": [
				"расшифровка"
			]
		},
		{
			"s": "鏡",
			"on": [
				"キョー"
			],
			"kun": [
				"かがみ"
			],
			"t": [
				"зеркало"
			]
		},
		{
			"s": "関",
			"on": [
				"カン"
			],
			"kun": [
				"かかわる",
				"せき"
			],
			"t": [
				"застава",
				"барьер",
				"иметь отношение"
			]
		}
	]
}